springdata/__init__.py
springdata/asyncio/__init__.py
springdata/asyncio/repository.py
springdata/domain/__init__.py
springdata/domain/page.py
springdata/domain/pageable.py
springdata/domain/sort.py
springdata/repository.py
spring_data_python-0.1.6.dist-info/LICENSE
spring_data_python-0.1.6.dist-info/WHEEL
spring_data_python-0.1.6.dist-info/METADATA
spring_data_python-0.1.6.dist-info/RECORD
